mqlTradeSim/Runner.py
mqlTradeSim/TestBot.py
mqlTradeSim/Time.py
mqlTradeSim/Utility.py
mqlTradeSim/__init__.py
mqlTradeSim/mqlTradeBot.py
mqlTradeSim-0.1.0.1.dist-info/METADATA
mqlTradeSim-0.1.0.1.dist-info/WHEEL
mqlTradeSim-0.1.0.1.dist-info/top_level.txt
mqlTradeSim-0.1.0.1.dist-info/RECORD
